network_jobs_data/__init__.py
network_jobs_data/hirefrank/advisor.json
network_jobs_data/hirefrank/ai-ml-nyc-mid.json
network_jobs_data/hirefrank/ai-ml-nyc-senior.json
network_jobs_data/hirefrank/ai-ml-other-mid.json
network_jobs_data/hirefrank/ai-ml-other-senior.json
network_jobs_data/hirefrank/ai-ml-remote-mid.json
network_jobs_data/hirefrank/ai-ml-remote-senior.json
network_jobs_data/hirefrank/ai-ml-sf-mid.json
network_jobs_data/hirefrank/ai-ml-sf-senior.json
network_jobs_data/hirefrank/ai-ml.json
network_jobs_data/hirefrank/customer-success-nyc-mid.json
network_jobs_data/hirefrank/customer-success-nyc-senior.json
network_jobs_data/hirefrank/customer-success-other-mid.json
network_jobs_data/hirefrank/customer-success-other-senior.json
network_jobs_data/hirefrank/customer-success-remote-mid.json
network_jobs_data/hirefrank/customer-success-remote-senior.json
network_jobs_data/hirefrank/customer-success-sf-mid.json
network_jobs_data/hirefrank/customer-success-sf-senior.json
network_jobs_data/hirefrank/customer-success.json
network_jobs_data/hirefrank/data-nyc-mid.json
network_jobs_data/hirefrank/data-nyc-senior.json
network_jobs_data/hirefrank/data-other-mid.json
network_jobs_data/hirefrank/data-other-senior.json
network_jobs_data/hirefrank/data-remote-mid.json
network_jobs_data/hirefrank/data-remote-senior.json
network_jobs_data/hirefrank/data-sf-mid.json
network_jobs_data/hirefrank/data-sf-senior.json
network_jobs_data/hirefrank/data.json
network_jobs_data/hirefrank/design-nyc-mid.json
network_jobs_data/hirefrank/design-nyc-senior.json
network_jobs_data/hirefrank/design-other-mid.json
network_jobs_data/hirefrank/design-other-senior.json
network_jobs_data/hirefrank/design-remote-mid.json
network_jobs_data/hirefrank/design-remote-senior.json
network_jobs_data/hirefrank/design-sf-mid.json
network_jobs_data/hirefrank/design-sf-senior.json
network_jobs_data/hirefrank/design.json
network_jobs_data/hirefrank/engineering-nyc-mid.json
network_jobs_data-0.0.20260111024211.dist-info/METADATA
network_jobs_data-0.0.20260111024211.dist-info/WHEEL
network_jobs_data-0.0.20260111024211.dist-info/top_level.txt
network_jobs_data-0.0.20260111024211.dist-info/RECORD
