Metadata-Version: 2.4
Name: network-jobs-data
Version: 0.0.20260111024211
Summary: Job listings from advisor networks for potential intro opportunities
Author: hirefrank
License: MIT
